mdpants/README.rst
mdpants/__init__.py
mdpants/constant_width.py
mdpants/mdpants.py
mdpants/version
mdpants/lists/emoticons.bin
mdpants/lists/emoticons.txt
mdpants/lists/words.bin
mdpants/lists/words.txt
mdpants-0.8.9.dist-info/DESCRIPTION.rst
mdpants-0.8.9.dist-info/METADATA
mdpants-0.8.9.dist-info/RECORD
mdpants-0.8.9.dist-info/WHEEL
mdpants-0.8.9.dist-info/entry_points.txt
mdpants-0.8.9.dist-info/metadata.json
mdpants-0.8.9.dist-info/top_level.txt
