Metadata-Version: 2.0
Name: mdpants
Version: 0.8.9
Summary: A small tool to generate deterministic, pronounceable and memorable words from a given input
Home-page: https://github.com/25A0/MustacheDonkeyPants
Author: Moritz Neikes
Author-email: moritz@post-apocalyptic-crypto.org
License: Public Domain
Keywords: tool hash deterministic pronounceable words
Platform: UNKNOWN
Classifier: Development Status :: 4 - Beta
Classifier: Intended Audience :: Developers
Classifier: License :: Public Domain
Classifier: Programming Language :: Python :: 2
Classifier: Programming Language :: Python :: 2.7
Requires-Dist: numpy
Provides-Extra: test
Requires-Dist: pytest; extra == 'test'
